wsgi_kerberos.py
WSGI_Kerberos-1.0.2.dist-info/AUTHORS
WSGI_Kerberos-1.0.2.dist-info/LICENSE
WSGI_Kerberos-1.0.2.dist-info/METADATA
WSGI_Kerberos-1.0.2.dist-info/WHEEL
WSGI_Kerberos-1.0.2.dist-info/top_level.txt
WSGI_Kerberos-1.0.2.dist-info/RECORD
