Metadata-Version: 2.1
Name: WSGI-Kerberos
Version: 1.0.2
Summary: Kerberos authentication support in WSGI Middleware
Home-page: https://github.com/deshaw/wsgi-kerberos
Author: Michael Komitee
Author-email: mkomitee@gmail.com
Maintainer: Vitaly Shupak
Maintainer-email: vitaly.shupak@deshaw.com
License: BSD-3-Clause
Platform: any
Classifier: Development Status :: 4 - Beta
Classifier: Environment :: Web Environment
Classifier: Intended Audience :: Developers
Classifier: License :: OSI Approved :: BSD License
Classifier: Operating System :: OS Independent
Classifier: Programming Language :: Python
Classifier: Programming Language :: Python :: 2.7
Classifier: Programming Language :: Python :: 3
Classifier: Topic :: Internet :: WWW/HTTP
Classifier: Topic :: Internet :: WWW/HTTP :: WSGI
Classifier: Topic :: Internet :: WWW/HTTP :: WSGI :: Middleware
Classifier: Topic :: Software Development :: Libraries :: Python Modules
License-File: LICENSE
License-File: AUTHORS
Requires-Dist: kerberos (<2)
